saur/__init__.py
saur/settings.py
saur/utils.py
saur/app/__init__.py
saur/app/fastapi.py
saur/mixins/__init__.py
saur/mixins/active.py
saur/mixins/async_access.py
saur/mixins/watch.py
saur/types/__init__.py
saur/types/delimited.py
saur/types/hashid.py
saur/types/numeric_datetime.py
saur/types/pydantic.py
saur/types/relativedelta.py
saur/types/uuid.py
saur-0.2.5.dist-info/LICENSE.txt
saur-0.2.5.dist-info/METADATA
saur-0.2.5.dist-info/WHEEL
saur-0.2.5.dist-info/top_level.txt
saur-0.2.5.dist-info/RECORD
