Metadata-Version: 2.1
Name: saur
Version: 0.2.5
Summary: SQL Alchemy Utilities Repository
Author-email: Michael Tartre <quantology.org@gmail.com>
Project-URL: Homepage, https://gitlab.com/sofet-dev/saur
Project-URL: Repository, https://gitlab.com/sofet-dev/saur.git
Project-URL: Issues, https://gitlab.com/sofet-dev/saur/-/issues
Classifier: Development Status :: 3 - Alpha
Classifier: License :: OSI Approved :: Mozilla Public License 2.0 (MPL 2.0)
Classifier: Natural Language :: English
Classifier: Operating System :: OS Independent
Classifier: Programming Language :: Python
Classifier: Programming Language :: Python :: 3.10
Classifier: Programming Language :: Python :: 3.11
Classifier: Programming Language :: Python :: 3.12
Requires-Python: >=3.10
License-File: LICENSE.txt
Requires-Dist: sqlalchemy >=2
Requires-Dist: pydantic-settings >=2
Provides-Extra: fastapi
Requires-Dist: fastapi ; extra == 'fastapi'
Provides-Extra: hashid
Requires-Dist: randseq ; extra == 'hashid'
